FDL_pytorch/FDL.py
FDL_pytorch/__init__.py
FDL_pytorch/models.py
FDL_pytorch-1.0.dist-info/METADATA
FDL_pytorch-1.0.dist-info/WHEEL
FDL_pytorch-1.0.dist-info/top_level.txt
FDL_pytorch-1.0.dist-info/RECORD
