Metadata-Version: 2.1
Name: FDL-pytorch
Version: 1.0
Summary: Frequency Distribution Loss (FDL) for misalignment data
Home-page: https://github.com/eezkni/FDL
Author: Zhangkai Ni, Juncheng Wu, Zian Wang
Author-email: zkni@tongji.edu.cn
License: MIT
Keywords: pytorch,loss,image transformation,misalignment
Platform: python
Requires-Dist: torch (>=1.0)
